text_autoencoder/__init__.py
text_autoencoder/__version__.py
text_autoencoder/inference.py
text_autoencoder/knn_classification.py
text_autoencoder/train.py
text_autoencoder/ae_exp/__init__.py
text_autoencoder/ae_exp/ae_1.py
text_autoencoder/ae_exp/ae_2.py
text_autoencoder/ae_exp/ae_3.py
text_autoencoder/ae_exp/ae_4.py
text_autoencoder/ae_exp/ae_5.py
text_autoencoder/ae_exp/ae_6.py
text_autoencoder/ae_exp/ae_7.py
text_autoencoder/ae_exp/ae_8.py
text_autoencoder/ae_exp/utils.py
text_autoencoder/ae_exp/vae_1.py
text_autoencoder/autoencoders/__init__.py
text_autoencoder/autoencoders/ae_1.py
text_autoencoder/autoencoders/base_autoencoder.py
text_autoencoder/autoencoders/decoders/__init__.py
text_autoencoder/autoencoders/decoders/lstm_attention_on_history.py
text_autoencoder/autoencoders/decoders/lstm_get_init_state.py
text_autoencoder/autoencoders/decoders/lstm_get_vector_n_init_state.py
text_autoencoder/autoencoders/decoders/test/__init__.py
text_autoencoder/autoencoders/decoders/test/data.py
text_autoencoder/autoencoders/decoders/test/test_lstm_attention_on_history.py
text_autoencoder/autoencoders/decoders/test/test_lstm_get_vector_n_init_state.py
text_autoencoder/autoencoders/encoders/__init__.py
text_autoencoder/autoencoders/encoders/dynamic_bidir_lstm.py
text_autoencoder/autoencoders/encoders/dynamic_lstm.py
text_autoencoder/autoencoders/encoders/lstm_with_self_attention.py
text_autoencoder/autoencoders/encoders/stacked_cnn.py
text_autoencoder/autoencoders/encoders/stacked_cnn_lstm.py
text_autoencoder/autoencoders/encoders/stacked_cnn_with_self_attention.py
text_autoencoder/autoencoders/encoders/test/__init__.py
text_autoencoder/autoencoders/encoders/test/data.py
text_autoencoder/autoencoders/encoders/test/test_dynamic_bidir_lstm.py
text_autoencoder/autoencoders/encoders/test/test_dynamic_lstm.py
text_autoencoder/autoencoders/encoders/test/test_lstm_with_self_attention.py
text_autoencoder-0.0.1.dist-info/METADATA
text_autoencoder-0.0.1.dist-info/RECORD
text_autoencoder-0.0.1.dist-info/WHEEL
text_autoencoder-0.0.1.dist-info/top_level.txt
