Metadata-Version: 2.1
Name: text-autoencoder
Version: 0.0.1
Summary: Yoctol Natural Language Text Autoencoder
Home-page: UNKNOWN
Author: Solumilken
License: MIT
Platform: UNKNOWN
Classifier: Programming Language :: Python
Classifier: Programming Language :: Python :: 3.6
Requires-Python: >=3.6
Requires-Dist: numpy (==1.14.2)
Requires-Dist: tensorflow (==1.7.0)
Requires-Dist: bistiming (==0.1.1)
Requires-Dist: mkdir-p (==0.1.1)
Requires-Dist: pyyaml (==3.13)
Requires-Dist: u-msgpack-python (==2.5.0)
Requires-Dist: tqdm (==4.23.4)
Requires-Dist: serving-utils (==0.4.3)
